logger/__init__.py
logger/log_formatter.py
logger/logger.py
logger/utils.py
elegant_logger-0.0.2.dist-info/LICENSE
elegant_logger-0.0.2.dist-info/METADATA
elegant_logger-0.0.2.dist-info/WHEEL
elegant_logger-0.0.2.dist-info/top_level.txt
elegant_logger-0.0.2.dist-info/RECORD
