Metadata-Version: 2.1
Name: elegant-logger
Version: 0.0.2
Author-email: Haotian Xie <hotinexie@gmail.com>
Project-URL: Homepage, https://github.com/elegant-infra/logger
Project-URL: Issues, https://github.com/elegant-infra/logger/issues
Classifier: Programming Language :: Python :: 3
Classifier: License :: OSI Approved :: MIT License
Classifier: Operating System :: OS Independent
Requires-Python: >=3.7
License-File: LICENSE
Requires-Dist: termcolor
